dulu/__init__.py
dulu/core.py
dulu/models.py
dulu/preprocessing.py
dulu-0.1.4.dist-info/LICENSE
dulu-0.1.4.dist-info/METADATA
dulu-0.1.4.dist-info/WHEEL
dulu-0.1.4.dist-info/top_level.txt
dulu-0.1.4.dist-info/RECORD
