Metadata-Version: 2.1
Name: dulu
Version: 0.1.4
Summary: A Python library for OCR
Home-page: https://github.com/whiletruelearn/florence_ocr
Author: Krishna Sangeeth
Author-email: kskrishnasangeeth@gmail.com
Classifier: Programming Language :: Python :: 3
Classifier: License :: OSI Approved :: MIT License
Classifier: Operating System :: OS Independent
Requires-Python: >=3.6
License-File: LICENSE
Requires-Dist: numpy==1.26.4
Requires-Dist: opencv-python==4.10.0.84
Requires-Dist: transformers==4.42.3
Requires-Dist: torch==2.3.1
Requires-Dist: timm==1.0.7
Requires-Dist: einops==0.8.0
